{
  "st7701s.display": {
    "schemas": {
      "CONFIG_SCHEMA": {
        "type": "schema",
        "schema": {
          "extends": [
            "display.FULL_DISPLAY_SCHEMA"
          ],
          "config_vars": {
            "id": {
              "key": "GeneratedID",
              "id_type": {
                "class": "st7701s::ST7701S",
                "parents": [
                  "display::Display",
                  "PollingComponent",
                  "Component",
                  "Component",
                  "spi::SPIDevice"
                ]
              },
              "docs": "**[ID](https://esphome.io/guides/configuration-types.html#config-id)**: Manually specify the ID used for code generation.\n\n*See also: [ST7701S Display Driver](https://esphome.io/components/display/st7701s.html#configuration-variables)*"
            },
            "dimensions": {
              "key": "Required",
              "type": "schema",
              "schema": {
                "config_vars": {
                  "width": {
                    "key": "Required",
                    "type": "integer",
                    "docs": "**int**: Specifies width of display.\n\n*See also: [ST7701S Display Driver](https://esphome.io/components/display/st7701s.html#configuration-variables)*"
                  },
                  "height": {
                    "key": "Required",
                    "type": "integer",
                    "docs": "**int**: Specifies height of display in pixels.\n\n*See also: [ST7701S Display Driver](https://esphome.io/components/display/st7701s.html#configuration-variables)*"
                  },
                  "offset_height": {
                    "key": "Optional",
                    "default": "0",
                    "type": "integer",
                    "docs": "**int**: Specify an offset for the y-direction of the display. Default is 0.\n\n*See also: [ST7701S Display Driver](https://esphome.io/components/display/st7701s.html#configuration-variables)*"
                  },
                  "offset_width": {
                    "key": "Optional",
                    "default": "0",
                    "type": "integer",
                    "docs": "**int**: Specify an offset for the x-direction of the display, typically used when an LCD is smaller than the maximum supported by the driver chip. Default is 0\n\n*See also: [ST7701S Display Driver](https://esphome.io/components/display/st7701s.html#configuration-variables)*"
                  }
                }
              },
              "docs": "Dimensions of the screen, specified either as *width* **x** *height* (e.g `320x240`) or with separate config keys.\n  * **height** (**Required**, int): Specifies height of display in pixels.\n  \n  * **width** (**Required**, int): Specifies width of display.\n  \n  * **offset_width** (*Optional*, int): Specify an offset for the x-direction of the display, typically used when an LCD is smaller than the maximum supported by the driver chip. Default is 0\n  \n  * **offset_height** (*Optional*, int): Specify an offset for the y-direction of the display. Default is 0.\n  \n  \n\n*See also: [ST7701S Display Driver](https://esphome.io/components/display/st7701s.html#configuration-variables)*"
            },
            "transform": {
              "key": "Optional",
              "type": "schema",
              "schema": {
                "config_vars": {
                  "mirror_x": {
                    "key": "Optional",
                    "default": "False",
                    "type": "boolean"
                  },
                  "mirror_y": {
                    "key": "Optional",
                    "default": "False",
                    "type": "boolean"
                  }
                }
              }
            },
            "data_pins": {
              "key": "Required",
              "type": "schema",
              "schema": {
                "config_vars": {
                  "red": {
                    "key": "Required"
                  },
                  "green": {
                    "key": "Required"
                  },
                  "blue": {
                    "key": "Required"
                  }
                }
              },
              "docs": "A list of pins used for the databus. Specified in 3 groups.\n  * **red**: (**Required**, [Pin Schema](https://esphome.io/guides/configuration-types.html#config-pin-schema)) Exactly 5 pin numbers for the red databits, listed from least to most significant bit.\n  \n  * **green**: (**Required**, [Pin Schema](https://esphome.io/guides/configuration-types.html#config-pin-schema)) Exactly 6 pin numbers for the green databits, listed from least to most significant bit.\n  \n  * **blue**: (**Required**, [Pin Schema](https://esphome.io/guides/configuration-types.html#config-pin-schema)) Exactly 5 pin numbers for the blue databits, listed from least to most significant bit.\n  \n  \n\n*See also: [ST7701S Display Driver](https://esphome.io/components/display/st7701s.html#configuration-variables)*"
            },
            "init_sequence": {
              "key": "Optional",
              "default": "1",
              "is_list": true,
              "docs": "**A list of byte arrays**: Specifies the init sequence for the display\n\n*See also: [ST7701S Display Driver](https://esphome.io/components/display/st7701s.html#configuration-variables)*"
            },
            "color_order": {
              "key": "Optional",
              "type": "enum",
              "values": {
                "RGB": null,
                "BGR": null
              },
              "docs": "Should be one of `bgr` (default) or `rgb`.\n\n*See also: [ST7701S Display Driver](https://esphome.io/components/display/st7701s.html#configuration-variables)*"
            },
            "pclk_frequency": {
              "key": "Optional",
              "default": "16MHz",
              "docs": "Set the pixel clock speed. Default is 8MHz.\n\n*See also: [ST7701S Display Driver](https://esphome.io/components/display/st7701s.html#configuration-variables)*"
            },
            "pclk_inverted": {
              "key": "Optional",
              "default": "True",
              "type": "boolean"
            },
            "invert_colors": {
              "key": "Optional",
              "default": "False",
              "type": "boolean"
            },
            "de_pin": {
              "key": "Required",
              "schema": true,
              "internal": true,
              "modes": [
                "output"
              ],
              "type": "pin",
              "docs": "**[Pin Schema](https://esphome.io/guides/configuration-types.html#config-pin-schema)**: The DE pin.\n\n*See also: [ST7701S Display Driver](https://esphome.io/components/display/st7701s.html#configuration-variables)*"
            },
            "pclk_pin": {
              "key": "Required",
              "schema": true,
              "internal": true,
              "modes": [
                "output"
              ],
              "type": "pin",
              "docs": "**[Pin Schema](https://esphome.io/guides/configuration-types.html#config-pin-schema)**: The PCLK pin.\n\n*See also: [ST7701S Display Driver](https://esphome.io/components/display/st7701s.html#configuration-variables)*"
            },
            "hsync_pin": {
              "key": "Required",
              "schema": true,
              "internal": true,
              "modes": [
                "output"
              ],
              "type": "pin",
              "docs": "**[Pin Schema](https://esphome.io/guides/configuration-types.html#config-pin-schema)**: The Horizontal sync pin.\n\n*See also: [ST7701S Display Driver](https://esphome.io/components/display/st7701s.html#configuration-variables)*"
            },
            "vsync_pin": {
              "key": "Required",
              "schema": true,
              "internal": true,
              "modes": [
                "output"
              ],
              "type": "pin",
              "docs": "**[Pin Schema](https://esphome.io/guides/configuration-types.html#config-pin-schema)**: The Vertical sync pin.\n\n*See also: [ST7701S Display Driver](https://esphome.io/components/display/st7701s.html#configuration-variables)*"
            },
            "reset_pin": {
              "key": "Optional",
              "schema": true,
              "modes": [
                "output"
              ],
              "type": "pin",
              "docs": "**[Pin Schema](https://esphome.io/guides/configuration-types.html#config-pin-schema)**: The RESET pin.\n\n*See also: [ST7701S Display Driver](https://esphome.io/components/display/st7701s.html#configuration-variables)*"
            },
            "dc_pin": {
              "key": "Optional",
              "schema": true,
              "modes": [
                "output"
              ],
              "type": "pin",
              "docs": "**[Pin Schema](https://esphome.io/guides/configuration-types.html#config-pin-schema)**: The DC pin.\n\n*See also: [ST7701S Display Driver](https://esphome.io/components/display/st7701s.html#configuration-variables)*"
            },
            "hsync_pulse_width": {
              "key": "Optional",
              "default": "10",
              "type": "integer",
              "docs": "**int**: The horizontal sync pulse width.\n\n*See also: [ST7701S Display Driver](https://esphome.io/components/display/st7701s.html#configuration-variables)*"
            },
            "hsync_back_porch": {
              "key": "Optional",
              "default": "10",
              "type": "integer",
              "docs": "**int**: The horizontal back porch length.\n\n*See also: [ST7701S Display Driver](https://esphome.io/components/display/st7701s.html#configuration-variables)*"
            },
            "hsync_front_porch": {
              "key": "Optional",
              "default": "20",
              "type": "integer",
              "docs": "**int**: The horizontal front porch length.\n\n*See also: [ST7701S Display Driver](https://esphome.io/components/display/st7701s.html#configuration-variables)*"
            },
            "vsync_pulse_width": {
              "key": "Optional",
              "default": "10",
              "type": "integer",
              "docs": "**int**: The vertical sync pulse width.\n\n*See also: [ST7701S Display Driver](https://esphome.io/components/display/st7701s.html#configuration-variables)*"
            },
            "vsync_back_porch": {
              "key": "Optional",
              "default": "10",
              "type": "integer",
              "docs": "**int**: The vertical back porch length.\n\n*See also: [ST7701S Display Driver](https://esphome.io/components/display/st7701s.html#configuration-variables)*"
            },
            "vsync_front_porch": {
              "key": "Optional",
              "default": "10",
              "type": "integer",
              "docs": "**int**: The vertical front porch length.\n\n*See also: [ST7701S Display Driver](https://esphome.io/components/display/st7701s.html#configuration-variables)*"
            },
            "spi_id": {
              "key": "GeneratedID",
              "use_id_type": "spi::SPIComponent",
              "type": "use_id"
            },
            "data_rate": {
              "key": "Optional",
              "default": "1000000.0",
              "type": "enum",
              "values": {
                "80000000.0": null,
                "40000000.0": null,
                "20000000.0": null,
                "10000000.0": null,
                "8000000.0": null,
                "5000000.0": null,
                "4000000.0": null,
                "2000000.0": null,
                "1000000.0": null,
                "200000.0": null,
                "75000.0": null,
                "1000.0": null
              }
            },
            "spi_mode": {
              "key": "Optional",
              "type": "enum",
              "values": {
                "MODE0": null,
                "MODE1": null,
                "MODE2": null,
                "MODE3": null,
                "0": null,
                "1": null,
                "2": null,
                "3": null
              }
            },
            "cs_pin": {
              "key": "Optional",
              "schema": true,
              "modes": [
                "output"
              ],
              "type": "pin"
            }
          }
        }
      }
    }
  }
}