{
  "uptime.sensor": {
    "schemas": {
      "CONFIG_SCHEMA": {
        "type": "typed",
        "types": {
          "seconds": {
            "extends": [
              "sensor.SENSOR_SCHEMA",
              "core.COMPONENT_SCHEMA"
            ],
            "config_vars": {
              "id": {
                "id_type": {
                  "class": "uptime::UptimeSecondsSensor",
                  "parents": [
                    "sensor::Sensor",
                    "EntityBase",
                    "PollingComponent",
                    "Component"
                  ]
                }
              },
              "unit_of_measurement": {
                "default": "s"
              },
              "icon": {
                "default": "mdi:timer-outline"
              },
              "accuracy_decimals": {
                "default": "0"
              },
              "device_class": {
                "default": "duration"
              },
              "state_class": {
                "default": "total_increasing"
              },
              "entity_category": {
                "default": "diagnostic"
              },
              "update_interval": {
                "key": "Optional",
                "default": "60s",
                "docs": "**[Time](https://esphome.io/guides/configuration-types.html#config-time)**: The sensor reporting interval. Defaults to `60s`. Valid only with `type: seconds`.\n\n*See also: [Uptime Sensor](https://esphome.io/components/sensor/uptime.html#configuration-variables)*"
              }
            }
          },
          "timestamp": {
            "extends": [
              "sensor.SENSOR_SCHEMA",
              "core.COMPONENT_SCHEMA"
            ],
            "config_vars": {
              "id": {
                "id_type": {
                  "class": "uptime::UptimeTimestampSensor",
                  "parents": [
                    "sensor::Sensor",
                    "EntityBase",
                    "Component"
                  ]
                }
              },
              "icon": {
                "default": "mdi:timer-outline"
              },
              "accuracy_decimals": {
                "default": "0"
              },
              "device_class": {
                "default": "timestamp"
              },
              "entity_category": {
                "default": "diagnostic"
              },
              "time_id": {
                "key": "GeneratedID",
                "use_id_type": "time::RealTimeClock",
                "type": "use_id"
              }
            }
          }
        },
        "typed_key": "type",
        "docs": "Either:\n  * `seconds` (*default*): A simple counter.\n  \n  * `timestamp`: presents the time ESPHome last booted up. Requires a [Time Component](https://esphome.io/components/time/index.html).\n  \n  \n\n*See also: [Uptime Sensor](https://esphome.io/components/sensor/uptime.html#configuration-variables)*"
      }
    }
  },
  "uptime.text_sensor": {
    "schemas": {
      "CONFIG_SCHEMA": {
        "type": "schema",
        "schema": {
          "extends": [
            "text_sensor.TEXT_SENSOR_SCHEMA",
            "core.COMPONENT_SCHEMA"
          ],
          "config_vars": {
            "id": {
              "id_type": {
                "class": "uptime::UptimeTextSensor",
                "parents": [
                  "text_sensor::TextSensor",
                  "EntityBase",
                  "PollingComponent",
                  "Component"
                ]
              }
            },
            "icon": {
              "default": "mdi:timer-outline"
            },
            "entity_category": {
              "default": "diagnostic"
            },
            "format": {
              "key": "Optional",
              "default": "{}",
              "type": "schema",
              "schema": {
                "config_vars": {
                  "days": {
                    "key": "Optional",
                    "default": "d",
                    "type": "string"
                  },
                  "hours": {
                    "key": "Optional",
                    "default": "h",
                    "type": "string"
                  },
                  "minutes": {
                    "key": "Optional",
                    "default": "m",
                    "type": "string"
                  },
                  "seconds": {
                    "key": "Optional",
                    "default": "s",
                    "type": "string"
                  },
                  "separator": {
                    "key": "Optional",
                    "default": "",
                    "type": "string"
                  },
                  "expand": {
                    "key": "Optional",
                    "default": "False",
                    "type": "boolean"
                  }
                }
              }
            },
            "update_interval": {
              "key": "Optional",
              "default": "30s",
              "docs": "**[Time](https://esphome.io/guides/configuration-types.html#config-time)**: The sensor reporting interval. Defaults to `30s`.\n\n*See also: [Uptime Text Sensor](https://esphome.io/components/text_sensor/uptime.html#configuration-variables)*"
            }
          }
        }
      }
    }
  }
}